grid/__init__.py
grid/bing_web_search.py
grid/cli.py
grid/grid.py
grid/webpage_clean.py
grid_research-0.1.5.dist-info/METADATA
grid_research-0.1.5.dist-info/WHEEL
grid_research-0.1.5.dist-info/top_level.txt
grid_research-0.1.5.dist-info/RECORD
