Metadata-Version: 2.1
Name: grid-research
Version: 0.1.5
Summary: A package for automated research data collection using LLMs and Web Search API
Home-page: https://github.com/bobcoi03/grid
Author: Your Name
Author-email: minh@everythingcompany.co
Classifier: Development Status :: 3 - Alpha
Classifier: Intended Audience :: Developers
Classifier: License :: OSI Approved :: MIT License
Classifier: Programming Language :: Python :: 3
Classifier: Programming Language :: Python :: 3.8
Classifier: Programming Language :: Python :: 3.9
Classifier: Programming Language :: Python :: 3.10
Requires-Python: >=3.8
Requires-Dist: openai==1.52.2
Requires-Dist: html2text
Requires-Dist: python-dotenv
Requires-Dist: aiohttp
Requires-Dist: beautifulsoup4
Requires-Dist: lxml
Requires-Dist: fake-useragent
Requires-Dist: pandas
Requires-Dist: pydantic>=2.0.0
Requires-Dist: requests
